kanoa/__init__.py
kanoa/cli.py
kanoa/config.py
kanoa/pricing.json
kanoa/pricing.py
kanoa/prompt_config.py
kanoa/backends/__init__.py
kanoa/backends/base.py
kanoa/backends/claude.py
kanoa/backends/example_custom_research.py
kanoa/backends/gemini.py
kanoa/backends/gemini_deep_research.py
kanoa/backends/github_copilot.py
kanoa/backends/openai.py
kanoa/converters/__init__.py
kanoa/converters/dataframe.py
kanoa/converters/figure.py
kanoa/converters/utils.py
kanoa/core/__init__.py
kanoa/core/interpreter.py
kanoa/core/token_guard.py
kanoa/core/types.py
kanoa/knowledge_base/__init__.py
kanoa/knowledge_base/base.py
kanoa/knowledge_base/cache.py
kanoa/knowledge_base/manager.py
kanoa/knowledge_base/vertex_rag.py
kanoa/tools/__init__.py
kanoa/tools/gemini_cache.py
kanoa/tools/vertex_rag.py
kanoa/utils/__init__.py
kanoa/utils/auth.py
kanoa/utils/cost_tracking.py
kanoa/utils/demo.py
kanoa/utils/logging.py
kanoa/utils/notebook.py
kanoa/utils/prompts.py
kanoa-0.5.0.dist-info/licenses/LICENSE
kanoa-0.5.0.dist-info/METADATA
kanoa-0.5.0.dist-info/WHEEL
kanoa-0.5.0.dist-info/entry_points.txt
kanoa-0.5.0.dist-info/top_level.txt
kanoa-0.5.0.dist-info/RECORD
