Metadata-Version: 2.4
Name: kanoa
Version: 0.5.0
Summary: AI-powered interpretation of data science outputs with multi-backend support
Home-page: https://github.com/lhzn-io/kanoa
Author: Daniel Fry
Author-email: dfry@lhzn.io
Keywords: ai llm data-science analytics gemini claude openai github-copilot jupyter
Classifier: Development Status :: 3 - Alpha
Classifier: Intended Audience :: Science/Research
Classifier: Intended Audience :: Developers
Classifier: License :: OSI Approved :: MIT License
Classifier: Operating System :: OS Independent
Classifier: Programming Language :: Python :: 3
Classifier: Programming Language :: Python :: 3.11
Classifier: Programming Language :: Python :: 3.12
Classifier: Topic :: Scientific/Engineering :: Artificial Intelligence
Classifier: Topic :: Scientific/Engineering :: Visualization
Requires-Python: >=3.11
License-File: LICENSE
Requires-Dist: matplotlib>=3.5.0
Requires-Dist: pandas>=1.3.0
Requires-Dist: pydantic>=2.0.0
Requires-Dist: PyYAML>=6.0.0
Provides-Extra: gemini
Requires-Dist: google-genai>=1.0.0; extra == "gemini"
Provides-Extra: claude
Requires-Dist: anthropic>=0.40.0; extra == "claude"
Provides-Extra: openai
Requires-Dist: openai>=1.0.0; extra == "openai"
Provides-Extra: github-copilot
Requires-Dist: github-copilot-sdk>=0.1.0; extra == "github-copilot"
Provides-Extra: local
Requires-Dist: openai>=1.0.0; extra == "local"
Provides-Extra: gcloud
Requires-Dist: google-cloud-storage>=2.0.0; extra == "gcloud"
Provides-Extra: vertexai
Requires-Dist: google-cloud-aiplatform>=1.40.0; extra == "vertexai"
Provides-Extra: notebook
Requires-Dist: ipython>=7.0.0; extra == "notebook"
Provides-Extra: all
Requires-Dist: google-genai>=1.0.0; extra == "all"
Requires-Dist: anthropic>=0.40.0; extra == "all"
Requires-Dist: openai>=1.0.0; extra == "all"
Requires-Dist: github-copilot-sdk>=0.1.0; extra == "all"
Requires-Dist: ipython>=7.0.0; extra == "all"
Requires-Dist: google-cloud-storage>=2.0.0; extra == "all"
Requires-Dist: google-cloud-aiplatform>=1.40.0; extra == "all"
Provides-Extra: backends
Requires-Dist: google-genai>=1.0.0; extra == "backends"
Requires-Dist: anthropic>=0.40.0; extra == "backends"
Requires-Dist: openai>=1.0.0; extra == "backends"
Requires-Dist: github-copilot-sdk>=0.1.0; extra == "backends"
Provides-Extra: dev
Requires-Dist: pytest>=7.0.0; extra == "dev"
Requires-Dist: pytest-cov>=4.0.0; extra == "dev"
Requires-Dist: python-dotenv>=1.0.0; extra == "dev"
Requires-Dist: ruff~=0.14.0; extra == "dev"
Requires-Dist: mypy>=1.0.0; extra == "dev"
Requires-Dist: pre-commit>=3.0.0; extra == "dev"
Requires-Dist: types-setuptools; extra == "dev"
Requires-Dist: types-PyYAML; extra == "dev"
Requires-Dist: types-requests; extra == "dev"
Requires-Dist: detect-secrets>=1.4.0; extra == "dev"
Requires-Dist: markitdown>=0.0.1; extra == "dev"
Requires-Dist: google-genai>=1.0.0; extra == "dev"
Requires-Dist: anthropic>=0.40.0; extra == "dev"
Requires-Dist: openai>=1.0.0; extra == "dev"
Requires-Dist: github-copilot-sdk>=0.1.0; extra == "dev"
Requires-Dist: ipython>=7.0.0; extra == "dev"
Requires-Dist: google-cloud-storage>=2.0.0; extra == "dev"
Requires-Dist: google-cloud-aiplatform>=1.40.0; extra == "dev"
Provides-Extra: docs
Requires-Dist: sphinx>=7.0.0; extra == "docs"
Requires-Dist: myst-parser>=2.0.0; extra == "docs"
Requires-Dist: sphinx-rtd-theme>=2.0.0; extra == "docs"
Requires-Dist: sphinx-autodoc-typehints>=1.20.0; extra == "docs"
Dynamic: author
Dynamic: author-email
Dynamic: classifier
Dynamic: description
Dynamic: description-content-type
Dynamic: home-page
Dynamic: keywords
Dynamic: license-file
Dynamic: provides-extra
Dynamic: requires-dist
Dynamic: requires-python
Dynamic: summary
